ote/__init__.py
ote/items.py
ote/settings.py
ote/spiders/__init__.py
ote/spiders/ote_electricity.py
python_ote-0.2.7.dist-info/WHEEL
python_ote-0.2.7.dist-info/METADATA
python_ote-0.2.7.dist-info/RECORD
