Metadata-Version: 2.4
Name: python-ote
Version: 0.2.7
Summary: Python library for scraping daily electricity prices from OTE (ote-cr.cz)
Keywords: scrapy,electricity,ote
Author: Dan Keder
Author-email: Dan Keder <dan.keder@protonmail.com>
License-Expression: Apache-2.0
Classifier: Programming Language :: Python :: 3
Classifier: Operating System :: OS Independent
Requires-Dist: scrapy<=2.13.0
Requires-Dist: python-dateutil
Requires-Python: >=3.9
Project-URL: Homepage, https://github.com/dankeder/python-ote
